queryset_serializer/__init__.py
queryset_serializer/db/__init__.py
queryset_serializer/db/models/__init__.py
queryset_serializer/serializers/__init__.py
queryset_serializer/serializers/model/__init__.py
queryset_serializer-1.0.4.dist-info/LICENSE
queryset_serializer-1.0.4.dist-info/METADATA
queryset_serializer-1.0.4.dist-info/WHEEL
queryset_serializer-1.0.4.dist-info/top_level.txt
queryset_serializer-1.0.4.dist-info/RECORD
