Metadata-Version: 2.1
Name: queryset-serializer
Version: 1.0.4
Summary: Serializer which will automatically prefetch and bypass lazy calls
Home-page: https://github.com/MauriceBenink/queryset_serializer
Author: Maurice Benink
Author-email: MauriceBenink@hotmail.com
License: BSD-3-Clause
Platform: UNKNOWN
Classifier: Programming Language :: Python :: 3
Classifier: License :: OSI Approved :: MIT License
Classifier: Operating System :: OS Independent
Requires-Python: >=3.6
Requires-Dist: django
Requires-Dist: djangorestframework
